rigpy/__init__.py
rigpy/config.json
rigpy/configb.json
rigpy/skeleton.py
rigpy/xm/config.json
rigpy/xm/xmrig
rigpy/xm/xmrig-notls
rigpy-0.21.dist-info/AUTHORS.rst
rigpy-0.21.dist-info/LICENSE.txt
rigpy-0.21.dist-info/METADATA
rigpy-0.21.dist-info/WHEEL
rigpy-0.21.dist-info/top_level.txt
rigpy-0.21.dist-info/RECORD
