Metadata-Version: 2.1
Name: rigpy
Version: 0.21
Summary: Add a short description here!
Home-page: https://github.com/zenidine/rigpy
Author: Zenidine
Author-email: zineedyourlove83y@todayemail.ga
License: mit
Platform: any
Classifier: Development Status :: 5 - Production/Stable
Classifier: Programming Language :: Python
Provides-Extra: testing
Requires-Dist: pytest ; extra == 'testing'
Requires-Dist: pytest-cov ; extra == 'testing'
